Lab4/Exercise2/src/StackController.v
`timescale 1ns / 1ps
//////////////////////////////////////////////////////////////////////////////////
// Create Date: 01/16/2025 01:45:42 AM
// Design Name: StackCircuit
// Module Name: StackController
// Project Name: StackCircuit
// Target Devices: Basys3
// Tool Versions: 2023.2
// Description: This module implements a Stack (LIFO) using an external RAM.
//              - An 8-bit value (from the switches) is pushed onto the stack
//                when the user presses the PUSH button (if the stack is not full).
//              - When the user presses the POP button and the stack is not empty,
//                the top-of-stack value is popped and sent to the display.
//              - The stack can store up to 256 elements.
//              - The StackCounter output shows the current number of elements
//                (saturating at 8'hFF when full), and StackValue holds the last
//                popped value.
//              - The RAM interface signals (RAMWriteEnable, RAMEnable,
//                RAMAddress, RAMDataIn) are generated accordingly.
//////////////////////////////////////////////////////////////////////////////////

module StackController (
    input  wire       Push,            // User push button
    input  wire       Pop,             // User pop button
    input  wire       Clk,
    input  wire       Reset,
    input  wire [7:0] DataIn,          // 8-bit value from the switches
    output wire [7:0] StackCounter,    // Number of elements currently in the stack
    output wire [7:0] StackValue,      // The popped value (to be displayed as two hex digits)
    output wire       RAMWriteEnable,  // Write enable for the external RAM
    output wire       RAMEnable,       // Enable for the external RAM
    output wire [7:0] RAMAddress,      // Address for the RAM access (0 to 255)
    output wire [7:0] RAMDataIn,       // Data input to the RAM
    input  wire [7:0] RAMDataOut       // Data output from the RAM
);

  reg [8:0] sp;
  reg [7:0] popped;

  assign StackValue = popped;
  assign StackCounter = (sp == 9'd256) ? 8'hFF : sp[7:0];

  // Manage Push Pop function
  always @(posedge Clk) begin
    if (Reset) begin
      sp <= 9'b0;
      popped <= 8'd0;
    end else begin
      if (Push && !Pop) begin
        if (sp < 9'd256) begin
          sp <= sp + 1;
        end
      end else if (Pop && !Push) begin
        if (sp > 0) begin  
          popped <= RAMDataOut;
          sp <= sp - 1;
        end
      end
    end
  end


  reg we;
  reg re;
  reg [7:0] addr, dataIn, dataOut;

  assign RAMWriteEnable = we;
  assign RAMEnable = re;
  assign RAMAddress = addr;
  assign RAMDataIn = dataIn;
  assign RAMDataOut = dataOut;

  always @(*) begin
    re = 1;
    if (Push && !Pop && sp < 9'd256) begin
      we = 1;
      addr = sp[7:0];
      dataIn = DataIn; 
    end else begin
      we = 0;
      if (sp > 0) begin
        addr = sp - 1;
      end else begin
        addr = 0;
      end
      dataIn = 0;
    end
  end

`ifdef COCOTB_SIM
  initial begin
    $dumpfile("waveform.vcd");  // Name of the dump file
    $dumpvars(0, StackController);  // Dump all variables for the top module
  end
`endif

endmodule

Lab4/Exercise2/cocotb/StackController/waveform.vcd
$date
	Mon Feb 03 19:47:38 2025
$end
$version
	Icarus Verilog
$end
$timescale
	1ps
$end
$scope module StackController $end
$var wire 1 ! Clk $end
$var wire 8 " DataIn [7:0] $end
$var wire 1 # Pop $end
$var wire 1 $ Push $end
$var wire 8 % RAMAddress [7:0] $end
$var wire 8 & RAMDataIn [7:0] $end
$var wire 8 ' RAMDataOut [7:0] $end
$var wire 1 ( RAMEnable $end
$var wire 1 ) RAMWriteEnable $end
$var wire 1 * Reset $end
$var wire 8 + StackValue [7:0] $end
$var wire 8 , StackCounter [7:0] $end
$var reg 8 - addr [7:0] $end
$var reg 8 . dataIn [7:0] $end
$var reg 8 / dataOut [7:0] $end
$var reg 8 0 popped [7:0] $end
$var reg 1 1 re $end
$var reg 9 2 sp [8:0] $end
$var reg 1 3 we $end
$upscope $end
$enddefinitions $end
$comment Show the parameter values. $end
$dumpall
$end
#0
$dumpvars
03
b0 2
11
b0 0
bx /
b0 .
b0 -
b0 ,
b0 +
1*
0)
1(
b0 '
b0 &
b0 %
0$
0#
b0 "
1!
$end
#5000
0!
#10000
1!
#15000
0!
#20000
b10010 &
b10010 .
1)
13
1$
b10010 "
1!
0*
#25000
0!
#30000
b0 &
b0 .
0)
03
0$
b1 ,
b0 %
b0 -
b1 2
1!
#35000
0!
#40000
b110100 &
b110100 .
b1 %
b1 -
1)
13
1$
b110100 "
1!
#45000
0!
#50000
b0 &
b0 .
0)
03
0$
b10 ,
b1 %
b1 -
b10 2
1!
#55000
0!
#60000
1#
b110100 '
1!
#65000
0!
#70000
0#
b1 ,
b0 %
b0 -
b1 2
b110100 +
b110100 0
1!
#75000
0!
#80000
1#
b10010 '
1!
#85000
0!
#90000
0#
b0 ,
b0 2
b10010 +
b10010 0
1!
