Lab1/src/Multiplexer.v
`timescale 1ns / 1ps
//////////////////////////////////////////////////////////////////////////////////
// Create Date: 12/23/2024 04:14:16 AM
// Design Name: Exercise1
// Module Name: Multiplexer
// Project Name: Exercise1
// Target Devices: Basys3
// Tool Versions: 2023.2
// Description: Multiplexer module to select between two hexadecimals input for 7-segment display
//////////////////////////////////////////////////////////////////////////////////


module Multiplexer (
    input  wire [3:0] In0,
    input  wire [3:0] In1,
    input  wire       Selector,
    output wire [3:0] DataOut
);
// Add code here //
    assign DataOut = (Selector) ? In1 : In0;
// End of code //

// cocotb dump waveforms
`ifdef COCOTB_SIM
initial begin
    $dumpfile("waveform.vcd");  // Name of the dump file
    $dumpvars(0, Multiplexer);  // Dump all variables for the top module
end
`endif
endmodule

Lab1/cocotb/MultiplexerTB/waveform.vcd
$date
	Tue Jan 14 13:32:28 2025
$end
$version
	Icarus Verilog
$end
$timescale
	1ps
$end
$scope module Multiplexer $end
$var wire 4 ! In0 [3:0] $end
$var wire 4 " In1 [3:0] $end
$var wire 1 # Selector $end
$var wire 4 $ DataOut [3:0] $end
$upscope $end
$enddefinitions $end
$comment Show the parameter values. $end
$dumpall
$end
#0
$dumpvars
b0 $
0#
b0 "
b0 !
$end
#1000
1#
#2000
0#
b1 "
#3000
b1 $
1#
#4000
b0 $
0#
b10 "
#5000
b10 $
1#
#6000
b0 $
0#
b11 "
#7000
b11 $
1#
#8000
b0 $
0#
b100 "
#9000
b100 $
1#
#10000
b0 $
0#
b101 "
#11000
b101 $
1#
#12000
b0 $
0#
b110 "
#13000
b110 $
1#
#14000
b0 $
0#
b111 "
#15000
b111 $
1#
#16000
b0 $
0#
b1000 "
#17000
b1000 $
1#
#18000
b0 $
0#
b1001 "
#19000
b1001 $
1#
#20000
b0 $
0#
b1010 "
#21000
b1010 $
1#
#22000
b0 $
0#
b1011 "
#23000
b1011 $
1#
#24000
b0 $
0#
b1100 "
#25000
b1100 $
1#
#26000
b0 $
0#
b1101 "
#27000
b1101 $
1#
#28000
b0 $
0#
b1110 "
#29000
b1110 $
1#
#30000
b0 $
0#
b1111 "
#31000
b1111 $
1#
#32000
b1 $
0#
b0 "
b1 !
#33000
b0 $
1#
#34000
b1 $
0#
b1 "
#35000
1#
#36000
0#
b10 "
#37000
b10 $
1#
#38000
b1 $
0#
b11 "
#39000
b11 $
1#
#40000
b1 $
0#
b100 "
#41000
b100 $
1#
#42000
b1 $
0#
b101 "
#43000
b101 $
1#
#44000
b1 $
0#
b110 "
#45000
b110 $
1#
#46000
b1 $
0#
b111 "
#47000
b111 $
1#
#48000
b1 $
0#
b1000 "
#49000
b1000 $
1#
#50000
b1 $
0#
b1001 "
#51000
b1001 $
1#
#52000
b1 $
0#
b1010 "
#53000
b1010 $
1#
#54000
b1 $
0#
b1011 "
#55000
b1011 $
1#
#56000
b1 $
0#
b1100 "
#57000
b1100 $
1#
#58000
b1 $
0#
b1101 "
#59000
b1101 $
1#
#60000
b1 $
0#
b1110 "
#61000
b1110 $
1#
#62000
b1 $
0#
b1111 "
#63000
b1111 $
1#
#64000
b10 $
0#
b0 "
b10 !
#65000
b0 $
1#
#66000
b10 $
0#
b1 "
#67000
b1 $
1#
#68000
b10 $
0#
b10 "
#69000
1#
#70000
0#
b11 "
#71000
b11 $
1#
#72000
b10 $
0#
b100 "
#73000
b100 $
1#
#74000
b10 $
0#
b101 "
#75000
b101 $
1#
#76000
b10 $
0#
b110 "
#77000
b110 $
1#
#78000
b10 $
0#
b111 "
#79000
b111 $
1#
#80000
b10 $
0#
b1000 "
#81000
b1000 $
1#
#82000
b10 $
0#
b1001 "
#83000
b1001 $
1#
#84000
b10 $
0#
b1010 "
#85000
b1010 $
1#
#86000
b10 $
0#
b1011 "
#87000
b1011 $
1#
#88000
b10 $
0#
b1100 "
#89000
b1100 $
1#
#90000
b10 $
0#
b1101 "
#91000
b1101 $
1#
#92000
b10 $
0#
b1110 "
#93000
b1110 $
1#
#94000
b10 $
0#
b1111 "
#95000
b1111 $
1#
#96000
b11 $
0#
b0 "
b11 !
#97000
b0 $
1#
#98000
b11 $
0#
b1 "
#99000
b1 $
1#
#100000
b11 $
0#
b10 "
#101000
b10 $
1#
#102000
b11 $
0#
b11 "
#103000
1#
#104000
0#
b100 "
#105000
b100 $
1#
#106000
b11 $
0#
b101 "
#107000
b101 $
1#
#108000
b11 $
0#
b110 "
#109000
b110 $
1#
#110000
b11 $
0#
b111 "
#111000
b111 $
1#
#112000
b11 $
0#
b1000 "
#113000
b1000 $
1#
#114000
b11 $
0#
b1001 "
#115000
b1001 $
1#
#116000
b11 $
0#
b1010 "
#117000
b1010 $
1#
#118000
b11 $
0#
b1011 "
#119000
b1011 $
1#
#120000
b11 $
0#
b1100 "
#121000
b1100 $
1#
#122000
b11 $
0#
b1101 "
#123000
b1101 $
1#
#124000
b11 $
0#
b1110 "
#125000
b1110 $
1#
#126000
b11 $
0#
b1111 "
#127000
b1111 $
1#
#128000
b100 $
0#
b0 "
b100 !
#129000
b0 $
1#
#130000
b100 $
0#
b1 "
#131000
b1 $
1#
#132000
b100 $
0#
b10 "
#133000
b10 $
1#
#134000
b100 $
0#
b11 "
#135000
b11 $
1#
#136000
b100 $
0#
b100 "
#137000
1#
#138000
0#
b101 "
#139000
b101 $
1#
#140000
b100 $
0#
b110 "
#141000
b110 $
1#
#142000
b100 $
0#
b111 "
#143000
b111 $
1#
#144000
b100 $
0#
b1000 "
#145000
b1000 $
1#
#146000
b100 $
0#
b1001 "
#147000
b1001 $
1#
#148000
b100 $
0#
b1010 "
#149000
b1010 $
1#
#150000
b100 $
0#
b1011 "
#151000
b1011 $
1#
#152000
b100 $
0#
b1100 "
#153000
b1100 $
1#
#154000
b100 $
0#
b1101 "
#155000
b1101 $
1#
#156000
b100 $
0#
b1110 "
#157000
b1110 $
1#
#158000
b100 $
0#
b1111 "
#159000
b1111 $
1#
#160000
b101 $
0#
b0 "
b101 !
#161000
b0 $
1#
#162000
b101 $
0#
b1 "
#163000
b1 $
1#
#164000
b101 $
0#
b10 "
#165000
b10 $
1#
#166000
b101 $
0#
b11 "
#167000
b11 $
1#
#168000
b101 $
0#
b100 "
#169000
b100 $
1#
#170000
b101 $
0#
b101 "
#171000
1#
#172000
0#
b110 "
#173000
b110 $
1#
#174000
b101 $
0#
b111 "
#175000
b111 $
1#
#176000
b101 $
0#
b1000 "
#177000
b1000 $
1#
#178000
b101 $
0#
b1001 "
#179000
b1001 $
1#
#180000
b101 $
0#
b1010 "
#181000
b1010 $
1#
#182000
b101 $
0#
b1011 "
#183000
b1011 $
1#
#184000
b101 $
0#
b1100 "
#185000
b1100 $
1#
#186000
b101 $
0#
b1101 "
#187000
b1101 $
1#
#188000
b101 $
0#
b1110 "
#189000
b1110 $
1#
#190000
b101 $
0#
b1111 "
#191000
b1111 $
1#
#192000
b110 $
0#
b0 "
b110 !
#193000
b0 $
1#
#194000
b110 $
0#
b1 "
#195000
b1 $
1#
#196000
b110 $
0#
b10 "
#197000
b10 $
1#
#198000
b110 $
0#
b11 "
#199000
b11 $
1#
#200000
b110 $
0#
b100 "
#201000
b100 $
1#
#202000
b110 $
0#
b101 "
#203000
b101 $
1#
#204000
b110 $
0#
b110 "
#205000
1#
#206000
0#
b111 "
#207000
b111 $
1#
#208000
b110 $
0#
b1000 "
#209000
b1000 $
1#
#210000
b110 $
0#
b1001 "
#211000
b1001 $
1#
#212000
b110 $
0#
b1010 "
#213000
b1010 $
1#
#214000
b110 $
0#
b1011 "
#215000
b1011 $
1#
#216000
b110 $
0#
b1100 "
#217000
b1100 $
1#
#218000
b110 $
0#
b1101 "
#219000
b1101 $
1#
#220000
b110 $
0#
b1110 "
#221000
b1110 $
1#
#222000
b110 $
0#
b1111 "
#223000
b1111 $
1#
#224000
b111 $
0#
b0 "
b111 !
#225000
b0 $
1#
#226000
b111 $
0#
b1 "
#227000
b1 $
1#
#228000
b111 $
0#
b10 "
#229000
b10 $
1#
#230000
b111 $
0#
b11 "
#231000
b11 $
1#
#232000
b111 $
0#
b100 "
#233000
b100 $
1#
#234000
b111 $
0#
b101 "
#235000
b101 $
1#
#236000
b111 $
0#
b110 "
#237000
b110 $
1#
#238000
b111 $
0#
b111 "
#239000
1#
#240000
0#
b1000 "
#241000
b1000 $
1#
#242000
b111 $
0#
b1001 "
#243000
b1001 $
1#
#244000
b111 $
0#
b1010 "
#245000
b1010 $
1#
#246000
b111 $
0#
b1011 "
#247000
b1011 $
1#
#248000
b111 $
0#
b1100 "
#249000
b1100 $
1#
#250000
b111 $
0#
b1101 "
#251000
b1101 $
1#
#252000
b111 $
0#
b1110 "
#253000
b1110 $
1#
#254000
b111 $
0#
b1111 "
#255000
b1111 $
1#
#256000
b1000 $
0#
b0 "
b1000 !
#257000
b0 $
1#
#258000
b1000 $
0#
b1 "
#259000
b1 $
1#
#260000
b1000 $
0#
b10 "
#261000
b10 $
1#
#262000
b1000 $
0#
b11 "
#263000
b11 $
1#
#264000
b1000 $
0#
b100 "
#265000
b100 $
1#
#266000
b1000 $
0#
b101 "
#267000
b101 $
1#
#268000
b1000 $
0#
b110 "
#269000
b110 $
1#
#270000
b1000 $
0#
b111 "
#271000
b111 $
1#
#272000
b1000 $
0#
b1000 "
#273000
1#
#274000
0#
b1001 "
#275000
b1001 $
1#
#276000
b1000 $
0#
b1010 "
#277000
b1010 $
1#
#278000
b1000 $
0#
b1011 "
#279000
b1011 $
1#
#280000
b1000 $
0#
b1100 "
#281000
b1100 $
1#
#282000
b1000 $
0#
b1101 "
#283000
b1101 $
1#
#284000
b1000 $
0#
b1110 "
#285000
b1110 $
1#
#286000
b1000 $
0#
b1111 "
#287000
b1111 $
1#
#288000
b1001 $
0#
b0 "
b1001 !
#289000
b0 $
1#
#290000
b1001 $
0#
b1 "
#291000
b1 $
1#
#292000
b1001 $
0#
b10 "
#293000
b10 $
1#
#294000
b1001 $
0#
b11 "
#295000
b11 $
1#
#296000
b1001 $
0#
b100 "
#297000
b100 $
1#
#298000
b1001 $
0#
b101 "
#299000
b101 $
1#
#300000
b1001 $
0#
b110 "
#301000
b110 $
1#
#302000
b1001 $
0#
b111 "
#303000
b111 $
1#
#304000
b1001 $
0#
b1000 "
#305000
b1000 $
1#
#306000
b1001 $
0#
b1001 "
#307000
1#
#308000
0#
b1010 "
#309000
b1010 $
1#
#310000
b1001 $
0#
b1011 "
#311000
b1011 $
1#
#312000
b1001 $
0#
b1100 "
#313000
b1100 $
1#
#314000
b1001 $
0#
b1101 "
#315000
b1101 $
1#
#316000
b1001 $
0#
b1110 "
#317000
b1110 $
1#
#318000
b1001 $
0#
b1111 "
#319000
b1111 $
1#
#320000
b1010 $
0#
b0 "
b1010 !
#321000
b0 $
1#
#322000
b1010 $
0#
b1 "
#323000
b1 $
1#
#324000
b1010 $
0#
b10 "
#325000
b10 $
1#
#326000
b1010 $
0#
b11 "
#327000
b11 $
1#
#328000
b1010 $
0#
b100 "
#329000
b100 $
1#
#330000
b1010 $
0#
b101 "
#331000
b101 $
1#
#332000
b1010 $
0#
b110 "
#333000
b110 $
1#
#334000
b1010 $
0#
b111 "
#335000
b111 $
1#
#336000
b1010 $
0#
b1000 "
#337000
b1000 $
1#
#338000
b1010 $
0#
b1001 "
#339000
b1001 $
1#
#340000
b1010 $
0#
b1010 "
#341000
1#
#342000
0#
b1011 "
#343000
b1011 $
1#
#344000
b1010 $
0#
b1100 "
#345000
b1100 $
1#
#346000
b1010 $
0#
b1101 "
#347000
b1101 $
1#
#348000
b1010 $
0#
b1110 "
#349000
b1110 $
1#
#350000
b1010 $
0#
b1111 "
#351000
b1111 $
1#
#352000
b1011 $
0#
b0 "
b1011 !
#353000
b0 $
1#
#354000
b1011 $
0#
b1 "
#355000
b1 $
1#
#356000
b1011 $
0#
b10 "
#357000
b10 $
1#
#358000
b1011 $
0#
b11 "
#359000
b11 $
1#
#360000
b1011 $
0#
b100 "
#361000
b100 $
1#
#362000
b1011 $
0#
b101 "
#363000
b101 $
1#
#364000
b1011 $
0#
b110 "
#365000
b110 $
1#
#366000
b1011 $
0#
b111 "
#367000
b111 $
1#
#368000
b1011 $
0#
b1000 "
#369000
b1000 $
1#
#370000
b1011 $
0#
b1001 "
#371000
b1001 $
1#
#372000
b1011 $
0#
b1010 "
#373000
b1010 $
1#
#374000
b1011 $
0#
b1011 "
#375000
1#
#376000
0#
b1100 "
#377000
b1100 $
1#
#378000
b1011 $
0#
b1101 "
#379000
b1101 $
1#
#380000
b1011 $
0#
b1110 "
#381000
b1110 $
1#
#382000
b1011 $
0#
b1111 "
#383000
b1111 $
1#
#384000
b1100 $
0#
b0 "
b1100 !
#385000
b0 $
1#
#386000
b1100 $
0#
b1 "
#387000
b1 $
1#
#388000
b1100 $
0#
b10 "
#389000
b10 $
1#
#390000
b1100 $
0#
b11 "
#391000
b11 $
1#
#392000
b1100 $
0#
b100 "
#393000
b100 $
1#
#394000
b1100 $
0#
b101 "
#395000
b101 $
1#
#396000
b1100 $
0#
b110 "
#397000
b110 $
1#
#398000
b1100 $
0#
b111 "
#399000
b111 $
1#
#400000
b1100 $
0#
b1000 "
#401000
b1000 $
1#
#402000
b1100 $
0#
b1001 "
#403000
b1001 $
1#
#404000
b1100 $
0#
b1010 "
#405000
b1010 $
1#
#406000
b1100 $
0#
b1011 "
#407000
b1011 $
1#
#408000
b1100 $
0#
b1100 "
#409000
1#
#410000
0#
b1101 "
#411000
b1101 $
1#
#412000
b1100 $
0#
b1110 "
#413000
b1110 $
1#
#414000
b1100 $
0#
b1111 "
#415000
b1111 $
1#
#416000
b1101 $
0#
b0 "
b1101 !
#417000
b0 $
1#
#418000
b1101 $
0#
b1 "
#419000
b1 $
1#
#420000
b1101 $
0#
b10 "
#421000
b10 $
1#
#422000
b1101 $
0#
b11 "
#423000
b11 $
1#
#424000
b1101 $
0#
b100 "
#425000
b100 $
1#
#426000
b1101 $
0#
b101 "
#427000
b101 $
1#
#428000
b1101 $
0#
b110 "
#429000
b110 $
1#
#430000
b1101 $
0#
b111 "
#431000
b111 $
1#
#432000
b1101 $
0#
b1000 "
#433000
b1000 $
1#
#434000
b1101 $
0#
b1001 "
#435000
b1001 $
1#
#436000
b1101 $
0#
b1010 "
#437000
b1010 $
1#
#438000
b1101 $
0#
b1011 "
#439000
b1011 $
1#
#440000
b1101 $
0#
b1100 "
#441000
b1100 $
1#
#442000
b1101 $
0#
b1101 "
#443000
1#
#444000
0#
b1110 "
#445000
b1110 $
1#
#446000
b1101 $
0#
b1111 "
#447000
b1111 $
1#
#448000
b1110 $
0#
b0 "
b1110 !
#449000
b0 $
1#
#450000
b1110 $
0#
b1 "
#451000
b1 $
1#
#452000
b1110 $
0#
b10 "
#453000
b10 $
1#
#454000
b1110 $
0#
b11 "
#455000
b11 $
1#
#456000
b1110 $
0#
b100 "
#457000
b100 $
1#
#458000
b1110 $
0#
b101 "
#459000
b101 $
1#
#460000
b1110 $
0#
b110 "
#461000
b110 $
1#
#462000
b1110 $
0#
b111 "
#463000
b111 $
1#
#464000
b1110 $
0#
b1000 "
#465000
b1000 $
1#
#466000
b1110 $
0#
b1001 "
#467000
b1001 $
1#
#468000
b1110 $
0#
b1010 "
#469000
b1010 $
1#
#470000
b1110 $
0#
b1011 "
#471000
b1011 $
1#
#472000
b1110 $
0#
b1100 "
#473000
b1100 $
1#
#474000
b1110 $
0#
b1101 "
#475000
b1101 $
1#
#476000
b1110 $
0#
b1110 "
#477000
1#
#478000
0#
b1111 "
#479000
b1111 $
1#
#480000
0#
b0 "
b1111 !
#481000
b0 $
1#
#482000
b1111 $
0#
b1 "
#483000
b1 $
1#
#484000
b1111 $
0#
b10 "
#485000
b10 $
1#
#486000
b1111 $
0#
b11 "
#487000
b11 $
1#
#488000
b1111 $
0#
b100 "
#489000
b100 $
1#
#490000
b1111 $
0#
b101 "
#491000
b101 $
1#
#492000
b1111 $
0#
b110 "
#493000
b110 $
1#
#494000
b1111 $
0#
b111 "
#495000
b111 $
1#
#496000
b1111 $
0#
b1000 "
#497000
b1000 $
1#
#498000
b1111 $
0#
b1001 "
#499000
b1001 $
1#
#500000
b1111 $
0#
b1010 "
#501000
b1010 $
1#
#502000
b1111 $
0#
b1011 "
#503000
b1011 $
1#
#504000
b1111 $
0#
b1100 "
#505000
b1100 $
1#
#506000
b1111 $
0#
b1101 "
#507000
b1101 $
1#
#508000
b1111 $
0#
b1110 "
#509000
b1110 $
1#
#510000
b1111 $
0#
b1111 "
#511000
1#
