Lab1/src/SevenSegmentDecoder.v
`timescale 1ns / 1ps
//////////////////////////////////////////////////////////////////////////////////
// Create Date: 12/23/2024 04:17:24 AM
// Design Name: Exercise1
// Module Name: SevenSegmentDecoder
// Project Name: Exercise1
// Target Devices: Basys3
// Tool Versions: 2023.2
// Description: Decoder for 7-segment display
//////////////////////////////////////////////////////////////////////////////////


module SevenSegmentDecoder (
    input  wire [3:0] DataIn,
    output wire [7:0] Segments
);
                                         
reg [7:0] segment_register;
  assign Segments = segment_register;

  always @(*) begin
    case (DataIn)
      4'b0000: segment_register = 8'b00000011; // 0
      4'b0001: segment_register = 8'b10011111; // 1
      4'b0010: segment_register = 8'b00100101; // 2
      4'b0011: segment_register = 8'b00001101; // 3
      4'b0100: segment_register = 8'b10011001; // 4
      4'b0101: segment_register = 8'b01001001; // 5
      4'b0110: segment_register = 8'b01000001; // 6
      4'b0111: segment_register = 8'b00011111; // 7
      4'b1000: segment_register = 8'b00000001; // 8
      4'b1001: segment_register = 8'b00001001; // 9
      4'b1010: segment_register = 8'b00010001; // A
      4'b1011: segment_register = 8'b11000001; // B
      4'b1100: segment_register = 8'b01100011; // C
      4'b1101: segment_register = 8'b10000101; // D
      4'b1110: segment_register = 8'b01100001; // E
      4'b1111: segment_register = 8'b01110001; // F
      default: segment_register = 8'b11111111; // All off
    endcase
  end                
  // End of code //

  // cocotb dump waveforms
`ifdef COCOTB_SIM
  initial begin
    $dumpfile("waveform.vcd");  // Name of the dump file
    $dumpvars(0, SevenSegmentDecoder);  // Dump all variables for the top module
  end
`endif
endmodule

Lab1/cocotb/SevenSegmentDecoderTB/waveform.vcd
$date
	Mon Jan 13 21:51:34 2025
$end
$version
	Icarus Verilog
$end
$timescale
	1ps
$end
$scope module SevenSegmentDecoder $end
$var wire 4 ! DataIn [3:0] $end
$var wire 8 " Segments [7:0] $end
$var reg 8 # segment_register [7:0] $end
$upscope $end
$enddefinitions $end
$comment Show the parameter values. $end
$dumpall
$end
#0
$dumpvars
b11 #
b11 "
b0 !
$end
#1000
b10011111 "
b10011111 #
b1 !
#2000
b100101 "
b100101 #
b10 !
#3000
b1101 "
b1101 #
b11 !
#4000
b10011001 "
b10011001 #
b100 !
#5000
b1001001 "
b1001001 #
b101 !
#6000
b1000001 "
b1000001 #
b110 !
#7000
b11111 "
b11111 #
b111 !
#8000
b1 "
b1 #
b1000 !
#9000
b1001 "
b1001 #
b1001 !
#10000
b10001 "
b10001 #
b1010 !
#11000
b11000001 "
b11000001 #
b1011 !
#12000
b1100011 "
b1100011 #
b1100 !
#13000
b10000101 "
b10000101 #
b1101 !
#14000
b1100001 "
b1100001 #
b1110 !
#15000
b1110001 "
b1110001 #
b1111 !
