Lab4/Exercise2/src/RAMUnit.v
`timescale 1ns / 1ps
//////////////////////////////////////////////////////////////////////////////////
// Create Date: 01/16/2025 01:45:27 AM
// Design Name: StackCircuit
// Module Name: RAMUnit
// Project Name: StackCircuit
// Target Devices: Basys3
// Tool Versions: 2023.2
// Description: Handle storing Data in the RAM.
//              This module implements a synchronous RAM with 256 locations.
//              On a rising edge of Clk, if RamEnable is asserted:
//                - If WriteEnable is high, DataIn is written to the memory
//                  at the given Address and the new value is output immediately.
//                - Otherwise, the data stored at Address is output.
//////////////////////////////////////////////////////////////////////////////////

module RAMUnit (
    input  wire       Clk,
    input  wire       Reset,
    input  wire       WriteEnable,
    input  wire       RamEnable,
    input  wire [7:0] Address,
    input  wire [7:0] DataIn,
    output wire [7:0] DataOut
);
  // Declare the memory: 256 words of 8 bits each.
  reg [7:0] mem[255:0];
  
  // A register to hold the data output.
  reg [7:0] dataOutReg;
  
  // Connect the internal register to the module output.
  assign DataOut = dataOutReg;
  
  // Synchronous process for memory read and write.
  // Using "write-first" behavior: when writing, the new DataIn is output.
  always @(posedge Clk) begin
    if (Reset) begin
      // On reset, clear the output register.
      dataOutReg <= 8'd0;
    end else if (RamEnable) begin
      if (WriteEnable) begin
        // Write operation: store DataIn into memory and output the new value.
        mem[Address]   <= DataIn;
        dataOutReg     <= DataIn;
      end else begin
        // Read operation: output the stored value at Address.
        dataOutReg     <= mem[Address];
      end
    end
  end

`ifdef COCOTB_SIM
  initial begin
    $dumpfile("waveform.vcd");  // Name of the dump file
    $dumpvars(0, RAMUnit);        // Dump all variables for the top module
  end
`endif

endmodule

Lab4/Exercise2/cocotb/RAMUnitTB/waveform.vcd
$date
	Mon Feb 03 19:01:14 2025
$end
$version
	Icarus Verilog
$end
$timescale
	1ps
$end
$scope module RAMUnit $end
$var wire 8 ! Address [7:0] $end
$var wire 1 " Clk $end
$var wire 8 # DataIn [7:0] $end
$var wire 8 $ DataOut [7:0] $end
$var wire 1 % RamEnable $end
$var wire 1 & Reset $end
$var wire 1 ' WriteEnable $end
$var reg 8 ( dataOutReg [7:0] $end
$upscope $end
$enddefinitions $end
$comment Show the parameter values. $end
$dumpall
$end
#0
$dumpvars
b0 (
0'
1&
0%
b0 $
b0 #
1"
b0 !
$end
#500
0"
#1000
1"
1%
1'
0&
#1500
0"
#2000
b1 $
b1 (
1"
b1 #
b1 !
#2500
0"
#3000
b10 $
b10 (
1"
b10 #
b10 !
#3500
0"
#4000
b11 $
b11 (
1"
b11 #
b11 !
#4500
0"
#5000
b100 $
b100 (
1"
b100 #
b100 !
#5500
0"
#6000
b101 $
b101 (
1"
b101 #
b101 !
#6500
0"
#7000
b110 $
b110 (
1"
b110 #
b110 !
#7500
0"
#8000
b111 $
b111 (
1"
b111 #
b111 !
#8500
0"
#9000
b1000 $
b1000 (
1"
b1000 #
b1000 !
#9500
0"
#10000
b1001 $
b1001 (
1"
b1001 #
b1001 !
#10500
0"
#11000
b1010 $
b1010 (
1"
b1010 #
b1010 !
#11500
0"
#12000
b1011 $
b1011 (
1"
b1011 #
b1011 !
#12500
0"
#13000
b1100 $
b1100 (
1"
b1100 #
b1100 !
#13500
0"
#14000
b1101 $
b1101 (
1"
b1101 #
b1101 !
#14500
0"
#15000
b1110 $
b1110 (
1"
b1110 #
b1110 !
#15500
0"
#16000
b1111 $
b1111 (
1"
b1111 #
b1111 !
#16500
0"
#17000
b10000 $
b10000 (
1"
b10000 #
b10000 !
#17500
0"
#18000
b10001 $
b10001 (
1"
b10001 #
b10001 !
#18500
0"
#19000
b10010 $
b10010 (
1"
b10010 #
b10010 !
#19500
0"
#20000
b10011 $
b10011 (
1"
b10011 #
b10011 !
#20500
0"
#21000
b10100 $
b10100 (
1"
b10100 #
b10100 !
#21500
0"
#22000
b10101 $
b10101 (
1"
b10101 #
b10101 !
#22500
0"
#23000
b10110 $
b10110 (
1"
b10110 #
b10110 !
#23500
0"
#24000
b10111 $
b10111 (
1"
b10111 #
b10111 !
#24500
0"
#25000
b11000 $
b11000 (
1"
b11000 #
b11000 !
#25500
0"
#26000
b11001 $
b11001 (
1"
b11001 #
b11001 !
#26500
0"
#27000
b11010 $
b11010 (
1"
b11010 #
b11010 !
#27500
0"
#28000
b11011 $
b11011 (
1"
b11011 #
b11011 !
#28500
0"
#29000
b11100 $
b11100 (
1"
b11100 #
b11100 !
#29500
0"
#30000
b11101 $
b11101 (
1"
b11101 #
b11101 !
#30500
0"
#31000
b11110 $
b11110 (
1"
b11110 #
b11110 !
#31500
0"
#32000
b11111 $
b11111 (
1"
b11111 #
b11111 !
#32500
0"
#33000
b100000 $
b100000 (
1"
b100000 #
b100000 !
#33500
0"
#34000
b100001 $
b100001 (
1"
b100001 #
b100001 !
#34500
0"
#35000
b100010 $
b100010 (
1"
b100010 #
b100010 !
#35500
0"
#36000
b100011 $
b100011 (
1"
b100011 #
b100011 !
#36500
0"
#37000
b100100 $
b100100 (
1"
b100100 #
b100100 !
#37500
0"
#38000
b100101 $
b100101 (
1"
b100101 #
b100101 !
#38500
0"
#39000
b100110 $
b100110 (
1"
b100110 #
b100110 !
#39500
0"
#40000
b100111 $
b100111 (
1"
b100111 #
b100111 !
#40500
0"
#41000
b101000 $
b101000 (
1"
b101000 #
b101000 !
#41500
0"
#42000
b101001 $
b101001 (
1"
b101001 #
b101001 !
#42500
0"
#43000
b101010 $
b101010 (
1"
b101010 #
b101010 !
#43500
0"
#44000
b101011 $
b101011 (
1"
b101011 #
b101011 !
#44500
0"
#45000
b101100 $
b101100 (
1"
b101100 #
b101100 !
#45500
0"
#46000
b101101 $
b101101 (
1"
b101101 #
b101101 !
#46500
0"
#47000
b101110 $
b101110 (
1"
b101110 #
b101110 !
#47500
0"
#48000
b101111 $
b101111 (
1"
b101111 #
b101111 !
#48500
0"
#49000
b110000 $
b110000 (
1"
b110000 #
b110000 !
#49500
0"
#50000
b110001 $
b110001 (
1"
b110001 #
b110001 !
#50500
0"
#51000
b110010 $
b110010 (
1"
b110010 #
b110010 !
#51500
0"
#52000
b110011 $
b110011 (
1"
b110011 #
b110011 !
#52500
0"
#53000
b110100 $
b110100 (
1"
b110100 #
b110100 !
#53500
0"
#54000
b110101 $
b110101 (
1"
b110101 #
b110101 !
#54500
0"
#55000
b110110 $
b110110 (
1"
b110110 #
b110110 !
#55500
0"
#56000
b110111 $
b110111 (
1"
b110111 #
b110111 !
#56500
0"
#57000
b111000 $
b111000 (
1"
b111000 #
b111000 !
#57500
0"
#58000
b111001 $
b111001 (
1"
b111001 #
b111001 !
#58500
0"
#59000
b111010 $
b111010 (
1"
b111010 #
b111010 !
#59500
0"
#60000
b111011 $
b111011 (
1"
b111011 #
b111011 !
#60500
0"
#61000
b111100 $
b111100 (
1"
b111100 #
b111100 !
#61500
0"
#62000
b111101 $
b111101 (
1"
b111101 #
b111101 !
#62500
0"
#63000
b111110 $
b111110 (
1"
b111110 #
b111110 !
#63500
0"
#64000
b111111 $
b111111 (
1"
b111111 #
b111111 !
#64500
0"
#65000
b1000000 $
b1000000 (
1"
b1000000 #
b1000000 !
#65500
0"
#66000
b1000001 $
b1000001 (
1"
b1000001 #
b1000001 !
#66500
0"
#67000
b1000010 $
b1000010 (
1"
b1000010 #
b1000010 !
#67500
0"
#68000
b1000011 $
b1000011 (
1"
b1000011 #
b1000011 !
#68500
0"
#69000
b1000100 $
b1000100 (
1"
b1000100 #
b1000100 !
#69500
0"
#70000
b1000101 $
b1000101 (
1"
b1000101 #
b1000101 !
#70500
0"
#71000
b1000110 $
b1000110 (
1"
b1000110 #
b1000110 !
#71500
0"
#72000
b1000111 $
b1000111 (
1"
b1000111 #
b1000111 !
#72500
0"
#73000
b1001000 $
b1001000 (
1"
b1001000 #
b1001000 !
#73500
0"
#74000
b1001001 $
b1001001 (
1"
b1001001 #
b1001001 !
#74500
0"
#75000
b1001010 $
b1001010 (
1"
b1001010 #
b1001010 !
#75500
0"
#76000
b1001011 $
b1001011 (
1"
b1001011 #
b1001011 !
#76500
0"
#77000
b1001100 $
b1001100 (
1"
b1001100 #
b1001100 !
#77500
0"
#78000
b1001101 $
b1001101 (
1"
b1001101 #
b1001101 !
#78500
0"
#79000
b1001110 $
b1001110 (
1"
b1001110 #
b1001110 !
#79500
0"
#80000
b1001111 $
b1001111 (
1"
b1001111 #
b1001111 !
#80500
0"
#81000
b1010000 $
b1010000 (
1"
b1010000 #
b1010000 !
#81500
0"
#82000
b1010001 $
b1010001 (
1"
b1010001 #
b1010001 !
#82500
0"
#83000
b1010010 $
b1010010 (
1"
b1010010 #
b1010010 !
#83500
0"
#84000
b1010011 $
b1010011 (
1"
b1010011 #
b1010011 !
#84500
0"
#85000
b1010100 $
b1010100 (
1"
b1010100 #
b1010100 !
#85500
0"
#86000
b1010101 $
b1010101 (
1"
b1010101 #
b1010101 !
#86500
0"
#87000
b1010110 $
b1010110 (
1"
b1010110 #
b1010110 !
#87500
0"
#88000
b1010111 $
b1010111 (
1"
b1010111 #
b1010111 !
#88500
0"
#89000
b1011000 $
b1011000 (
1"
b1011000 #
b1011000 !
#89500
0"
#90000
b1011001 $
b1011001 (
1"
b1011001 #
b1011001 !
#90500
0"
#91000
b1011010 $
b1011010 (
1"
b1011010 #
b1011010 !
#91500
0"
#92000
b1011011 $
b1011011 (
1"
b1011011 #
b1011011 !
#92500
0"
#93000
b1011100 $
b1011100 (
1"
b1011100 #
b1011100 !
#93500
0"
#94000
b1011101 $
b1011101 (
1"
b1011101 #
b1011101 !
#94500
0"
#95000
b1011110 $
b1011110 (
1"
b1011110 #
b1011110 !
#95500
0"
#96000
b1011111 $
b1011111 (
1"
b1011111 #
b1011111 !
#96500
0"
#97000
b1100000 $
b1100000 (
1"
b1100000 #
b1100000 !
#97500
0"
#98000
b1100001 $
b1100001 (
1"
b1100001 #
b1100001 !
#98500
0"
#99000
b1100010 $
b1100010 (
1"
b1100010 #
b1100010 !
#99500
0"
#100000
b1100011 $
b1100011 (
1"
b1100011 #
b1100011 !
#100500
0"
#101000
b1100100 $
b1100100 (
1"
b1100100 #
b1100100 !
#101500
0"
#102000
b1100101 $
b1100101 (
1"
b1100101 #
b1100101 !
#102500
0"
#103000
b1100110 $
b1100110 (
1"
b1100110 #
b1100110 !
#103500
0"
#104000
b1100111 $
b1100111 (
1"
b1100111 #
b1100111 !
#104500
0"
#105000
b1101000 $
b1101000 (
1"
b1101000 #
b1101000 !
#105500
0"
#106000
b1101001 $
b1101001 (
1"
b1101001 #
b1101001 !
#106500
0"
#107000
b1101010 $
b1101010 (
1"
b1101010 #
b1101010 !
#107500
0"
#108000
b1101011 $
b1101011 (
1"
b1101011 #
b1101011 !
#108500
0"
#109000
b1101100 $
b1101100 (
1"
b1101100 #
b1101100 !
#109500
0"
#110000
b1101101 $
b1101101 (
1"
b1101101 #
b1101101 !
#110500
0"
#111000
b1101110 $
b1101110 (
1"
b1101110 #
b1101110 !
#111500
0"
#112000
b1101111 $
b1101111 (
1"
b1101111 #
b1101111 !
#112500
0"
#113000
b1110000 $
b1110000 (
1"
b1110000 #
b1110000 !
#113500
0"
#114000
b1110001 $
b1110001 (
1"
b1110001 #
b1110001 !
#114500
0"
#115000
b1110010 $
b1110010 (
1"
b1110010 #
b1110010 !
#115500
0"
#116000
b1110011 $
b1110011 (
1"
b1110011 #
b1110011 !
#116500
0"
#117000
b1110100 $
b1110100 (
1"
b1110100 #
b1110100 !
#117500
0"
#118000
b1110101 $
b1110101 (
1"
b1110101 #
b1110101 !
#118500
0"
#119000
b1110110 $
b1110110 (
1"
b1110110 #
b1110110 !
#119500
0"
#120000
b1110111 $
b1110111 (
1"
b1110111 #
b1110111 !
#120500
0"
#121000
b1111000 $
b1111000 (
1"
b1111000 #
b1111000 !
#121500
0"
#122000
b1111001 $
b1111001 (
1"
b1111001 #
b1111001 !
#122500
0"
#123000
b1111010 $
b1111010 (
1"
b1111010 #
b1111010 !
#123500
0"
#124000
b1111011 $
b1111011 (
1"
b1111011 #
b1111011 !
#124500
0"
#125000
b1111100 $
b1111100 (
1"
b1111100 #
b1111100 !
#125500
0"
#126000
b1111101 $
b1111101 (
1"
b1111101 #
b1111101 !
#126500
0"
#127000
b1111110 $
b1111110 (
1"
b1111110 #
b1111110 !
#127500
0"
#128000
b1111111 $
b1111111 (
1"
b1111111 #
b1111111 !
#128500
0"
#129000
b10000000 $
b10000000 (
1"
b10000000 #
b10000000 !
#129500
0"
#130000
b10000001 $
b10000001 (
1"
b10000001 #
b10000001 !
#130500
0"
#131000
b10000010 $
b10000010 (
1"
b10000010 #
b10000010 !
#131500
0"
#132000
b10000011 $
b10000011 (
1"
b10000011 #
b10000011 !
#132500
0"
#133000
b10000100 $
b10000100 (
1"
b10000100 #
b10000100 !
#133500
0"
#134000
b10000101 $
b10000101 (
1"
b10000101 #
b10000101 !
#134500
0"
#135000
b10000110 $
b10000110 (
1"
b10000110 #
b10000110 !
#135500
0"
#136000
b10000111 $
b10000111 (
1"
b10000111 #
b10000111 !
#136500
0"
#137000
b10001000 $
b10001000 (
1"
b10001000 #
b10001000 !
#137500
0"
#138000
b10001001 $
b10001001 (
1"
b10001001 #
b10001001 !
#138500
0"
#139000
b10001010 $
b10001010 (
1"
b10001010 #
b10001010 !
#139500
0"
#140000
b10001011 $
b10001011 (
1"
b10001011 #
b10001011 !
#140500
0"
#141000
b10001100 $
b10001100 (
1"
b10001100 #
b10001100 !
#141500
0"
#142000
b10001101 $
b10001101 (
1"
b10001101 #
b10001101 !
#142500
0"
#143000
b10001110 $
b10001110 (
1"
b10001110 #
b10001110 !
#143500
0"
#144000
b10001111 $
b10001111 (
1"
b10001111 #
b10001111 !
#144500
0"
#145000
b10010000 $
b10010000 (
1"
b10010000 #
b10010000 !
#145500
0"
#146000
b10010001 $
b10010001 (
1"
b10010001 #
b10010001 !
#146500
0"
#147000
b10010010 $
b10010010 (
1"
b10010010 #
b10010010 !
#147500
0"
#148000
b10010011 $
b10010011 (
1"
b10010011 #
b10010011 !
#148500
0"
#149000
b10010100 $
b10010100 (
1"
b10010100 #
b10010100 !
#149500
0"
#150000
b10010101 $
b10010101 (
1"
b10010101 #
b10010101 !
#150500
0"
#151000
b10010110 $
b10010110 (
1"
b10010110 #
b10010110 !
#151500
0"
#152000
b10010111 $
b10010111 (
1"
b10010111 #
b10010111 !
#152500
0"
#153000
b10011000 $
b10011000 (
1"
b10011000 #
b10011000 !
#153500
0"
#154000
b10011001 $
b10011001 (
1"
b10011001 #
b10011001 !
#154500
0"
#155000
b10011010 $
b10011010 (
1"
b10011010 #
b10011010 !
#155500
0"
#156000
b10011011 $
b10011011 (
1"
b10011011 #
b10011011 !
#156500
0"
#157000
b10011100 $
b10011100 (
1"
b10011100 #
b10011100 !
#157500
0"
#158000
b10011101 $
b10011101 (
1"
b10011101 #
b10011101 !
#158500
0"
#159000
b10011110 $
b10011110 (
1"
b10011110 #
b10011110 !
#159500
0"
#160000
b10011111 $
b10011111 (
1"
b10011111 #
b10011111 !
#160500
0"
#161000
b10100000 $
b10100000 (
1"
b10100000 #
b10100000 !
#161500
0"
#162000
b10100001 $
b10100001 (
1"
b10100001 #
b10100001 !
#162500
0"
#163000
b10100010 $
b10100010 (
1"
b10100010 #
b10100010 !
#163500
0"
#164000
b10100011 $
b10100011 (
1"
b10100011 #
b10100011 !
#164500
0"
#165000
b10100100 $
b10100100 (
1"
b10100100 #
b10100100 !
#165500
0"
#166000
b10100101 $
b10100101 (
1"
b10100101 #
b10100101 !
#166500
0"
#167000
b10100110 $
b10100110 (
1"
b10100110 #
b10100110 !
#167500
0"
#168000
b10100111 $
b10100111 (
1"
b10100111 #
b10100111 !
#168500
0"
#169000
b10101000 $
b10101000 (
1"
b10101000 #
b10101000 !
#169500
0"
#170000
b10101001 $
b10101001 (
1"
b10101001 #
b10101001 !
#170500
0"
#171000
b10101010 $
b10101010 (
1"
b10101010 #
b10101010 !
#171500
0"
#172000
b10101011 $
b10101011 (
1"
b10101011 #
b10101011 !
#172500
0"
#173000
b10101100 $
b10101100 (
1"
b10101100 #
b10101100 !
#173500
0"
#174000
b10101101 $
b10101101 (
1"
b10101101 #
b10101101 !
#174500
0"
#175000
b10101110 $
b10101110 (
1"
b10101110 #
b10101110 !
#175500
0"
#176000
b10101111 $
b10101111 (
1"
b10101111 #
b10101111 !
#176500
0"
#177000
b10110000 $
b10110000 (
1"
b10110000 #
b10110000 !
#177500
0"
#178000
b10110001 $
b10110001 (
1"
b10110001 #
b10110001 !
#178500
0"
#179000
b10110010 $
b10110010 (
1"
b10110010 #
b10110010 !
#179500
0"
#180000
b10110011 $
b10110011 (
1"
b10110011 #
b10110011 !
#180500
0"
#181000
b10110100 $
b10110100 (
1"
b10110100 #
b10110100 !
#181500
0"
#182000
b10110101 $
b10110101 (
1"
b10110101 #
b10110101 !
#182500
0"
#183000
b10110110 $
b10110110 (
1"
b10110110 #
b10110110 !
#183500
0"
#184000
b10110111 $
b10110111 (
1"
b10110111 #
b10110111 !
#184500
0"
#185000
b10111000 $
b10111000 (
1"
b10111000 #
b10111000 !
#185500
0"
#186000
b10111001 $
b10111001 (
1"
b10111001 #
b10111001 !
#186500
0"
#187000
b10111010 $
b10111010 (
1"
b10111010 #
b10111010 !
#187500
0"
#188000
b10111011 $
b10111011 (
1"
b10111011 #
b10111011 !
#188500
0"
#189000
b10111100 $
b10111100 (
1"
b10111100 #
b10111100 !
#189500
0"
#190000
b10111101 $
b10111101 (
1"
b10111101 #
b10111101 !
#190500
0"
#191000
b10111110 $
b10111110 (
1"
b10111110 #
b10111110 !
#191500
0"
#192000
b10111111 $
b10111111 (
1"
b10111111 #
b10111111 !
#192500
0"
#193000
b11000000 $
b11000000 (
1"
b11000000 #
b11000000 !
#193500
0"
#194000
b11000001 $
b11000001 (
1"
b11000001 #
b11000001 !
#194500
0"
#195000
b11000010 $
b11000010 (
1"
b11000010 #
b11000010 !
#195500
0"
#196000
b11000011 $
b11000011 (
1"
b11000011 #
b11000011 !
#196500
0"
#197000
b11000100 $
b11000100 (
1"
b11000100 #
b11000100 !
#197500
0"
#198000
b11000101 $
b11000101 (
1"
b11000101 #
b11000101 !
#198500
0"
#199000
b11000110 $
b11000110 (
1"
b11000110 #
b11000110 !
#199500
0"
#200000
b11000111 $
b11000111 (
1"
b11000111 #
b11000111 !
#200500
0"
#201000
b11001000 $
b11001000 (
1"
b11001000 #
b11001000 !
#201500
0"
#202000
b11001001 $
b11001001 (
1"
b11001001 #
b11001001 !
#202500
0"
#203000
b11001010 $
b11001010 (
1"
b11001010 #
b11001010 !
#203500
0"
#204000
b11001011 $
b11001011 (
1"
b11001011 #
b11001011 !
#204500
0"
#205000
b11001100 $
b11001100 (
1"
b11001100 #
b11001100 !
#205500
0"
#206000
b11001101 $
b11001101 (
1"
b11001101 #
b11001101 !
#206500
0"
#207000
b11001110 $
b11001110 (
1"
b11001110 #
b11001110 !
#207500
0"
#208000
b11001111 $
b11001111 (
1"
b11001111 #
b11001111 !
#208500
0"
#209000
b11010000 $
b11010000 (
1"
b11010000 #
b11010000 !
#209500
0"
#210000
b11010001 $
b11010001 (
1"
b11010001 #
b11010001 !
#210500
0"
#211000
b11010010 $
b11010010 (
1"
b11010010 #
b11010010 !
#211500
0"
#212000
b11010011 $
b11010011 (
1"
b11010011 #
b11010011 !
#212500
0"
#213000
b11010100 $
b11010100 (
1"
b11010100 #
b11010100 !
#213500
0"
#214000
b11010101 $
b11010101 (
1"
b11010101 #
b11010101 !
#214500
0"
#215000
b11010110 $
b11010110 (
1"
b11010110 #
b11010110 !
#215500
0"
#216000
b11010111 $
b11010111 (
1"
b11010111 #
b11010111 !
#216500
0"
#217000
b11011000 $
b11011000 (
1"
b11011000 #
b11011000 !
#217500
0"
#218000
b11011001 $
b11011001 (
1"
b11011001 #
b11011001 !
#218500
0"
#219000
b11011010 $
b11011010 (
1"
b11011010 #
b11011010 !
#219500
0"
#220000
b11011011 $
b11011011 (
1"
b11011011 #
b11011011 !
#220500
0"
#221000
b11011100 $
b11011100 (
1"
b11011100 #
b11011100 !
#221500
0"
#222000
b11011101 $
b11011101 (
1"
b11011101 #
b11011101 !
#222500
0"
#223000
b11011110 $
b11011110 (
1"
b11011110 #
b11011110 !
#223500
0"
#224000
b11011111 $
b11011111 (
1"
b11011111 #
b11011111 !
#224500
0"
#225000
b11100000 $
b11100000 (
1"
b11100000 #
b11100000 !
#225500
0"
#226000
b11100001 $
b11100001 (
1"
b11100001 #
b11100001 !
#226500
0"
#227000
b11100010 $
b11100010 (
1"
b11100010 #
b11100010 !
#227500
0"
#228000
b11100011 $
b11100011 (
1"
b11100011 #
b11100011 !
#228500
0"
#229000
b11100100 $
b11100100 (
1"
b11100100 #
b11100100 !
#229500
0"
#230000
b11100101 $
b11100101 (
1"
b11100101 #
b11100101 !
#230500
0"
#231000
b11100110 $
b11100110 (
1"
b11100110 #
b11100110 !
#231500
0"
#232000
b11100111 $
b11100111 (
1"
b11100111 #
b11100111 !
#232500
0"
#233000
b11101000 $
b11101000 (
1"
b11101000 #
b11101000 !
#233500
0"
#234000
b11101001 $
b11101001 (
1"
b11101001 #
b11101001 !
#234500
0"
#235000
b11101010 $
b11101010 (
1"
b11101010 #
b11101010 !
#235500
0"
#236000
b11101011 $
b11101011 (
1"
b11101011 #
b11101011 !
#236500
0"
#237000
b11101100 $
b11101100 (
1"
b11101100 #
b11101100 !
#237500
0"
#238000
b11101101 $
b11101101 (
1"
b11101101 #
b11101101 !
#238500
0"
#239000
b11101110 $
b11101110 (
1"
b11101110 #
b11101110 !
#239500
0"
#240000
b11101111 $
b11101111 (
1"
b11101111 #
b11101111 !
#240500
0"
#241000
b11110000 $
b11110000 (
1"
b11110000 #
b11110000 !
#241500
0"
#242000
b11110001 $
b11110001 (
1"
b11110001 #
b11110001 !
#242500
0"
#243000
b11110010 $
b11110010 (
1"
b11110010 #
b11110010 !
#243500
0"
#244000
b11110011 $
b11110011 (
1"
b11110011 #
b11110011 !
#244500
0"
#245000
b11110100 $
b11110100 (
1"
b11110100 #
b11110100 !
#245500
0"
#246000
b11110101 $
b11110101 (
1"
b11110101 #
b11110101 !
#246500
0"
#247000
b11110110 $
b11110110 (
1"
b11110110 #
b11110110 !
#247500
0"
#248000
b11110111 $
b11110111 (
1"
b11110111 #
b11110111 !
#248500
0"
#249000
b11111000 $
b11111000 (
1"
b11111000 #
b11111000 !
#249500
0"
#250000
b11111001 $
b11111001 (
1"
b11111001 #
b11111001 !
#250500
0"
#251000
b11111010 $
b11111010 (
1"
b11111010 #
b11111010 !
#251500
0"
#252000
b11111011 $
b11111011 (
1"
b11111011 #
b11111011 !
#252500
0"
#253000
b11111100 $
b11111100 (
1"
b11111100 #
b11111100 !
#253500
0"
#254000
b11111101 $
b11111101 (
1"
b11111101 #
b11111101 !
#254500
0"
#255000
b11111110 $
b11111110 (
1"
b11111110 #
b11111110 !
#255500
0"
#256000
b11111111 $
b11111111 (
1"
b11111111 #
b11111111 !
#256500
0"
#257000
b0 $
b0 (
1"
b0 !
0'
#257500
0"
#258000
b1 $
b1 (
1"
b1 !
#258500
0"
#259000
b10 $
b10 (
1"
b10 !
#259500
0"
#260000
b11 $
b11 (
1"
b11 !
#260500
0"
#261000
b100 $
b100 (
1"
b100 !
#261500
0"
#262000
b101 $
b101 (
1"
b101 !
#262500
0"
#263000
b110 $
b110 (
1"
b110 !
#263500
0"
#264000
b111 $
b111 (
1"
b111 !
#264500
0"
#265000
b1000 $
b1000 (
1"
b1000 !
#265500
0"
#266000
b1001 $
b1001 (
1"
b1001 !
#266500
0"
#267000
b1010 $
b1010 (
1"
b1010 !
#267500
0"
#268000
b1011 $
b1011 (
1"
b1011 !
#268500
0"
#269000
b1100 $
b1100 (
1"
b1100 !
#269500
0"
#270000
b1101 $
b1101 (
1"
b1101 !
#270500
0"
#271000
b1110 $
b1110 (
1"
b1110 !
#271500
0"
#272000
b1111 $
b1111 (
1"
b1111 !
#272500
0"
#273000
b10000 $
b10000 (
1"
b10000 !
#273500
0"
#274000
b10001 $
b10001 (
1"
b10001 !
#274500
0"
#275000
b10010 $
b10010 (
1"
b10010 !
#275500
0"
#276000
b10011 $
b10011 (
1"
b10011 !
#276500
0"
#277000
b10100 $
b10100 (
1"
b10100 !
#277500
0"
#278000
b10101 $
b10101 (
1"
b10101 !
#278500
0"
#279000
b10110 $
b10110 (
1"
b10110 !
#279500
0"
#280000
b10111 $
b10111 (
1"
b10111 !
#280500
0"
#281000
b11000 $
b11000 (
1"
b11000 !
#281500
0"
#282000
b11001 $
b11001 (
1"
b11001 !
#282500
0"
#283000
b11010 $
b11010 (
1"
b11010 !
#283500
0"
#284000
b11011 $
b11011 (
1"
b11011 !
#284500
0"
#285000
b11100 $
b11100 (
1"
b11100 !
#285500
0"
#286000
b11101 $
b11101 (
1"
b11101 !
#286500
0"
#287000
b11110 $
b11110 (
1"
b11110 !
#287500
0"
#288000
b11111 $
b11111 (
1"
b11111 !
#288500
0"
#289000
b100000 $
b100000 (
1"
b100000 !
#289500
0"
#290000
b100001 $
b100001 (
1"
b100001 !
#290500
0"
#291000
b100010 $
b100010 (
1"
b100010 !
#291500
0"
#292000
b100011 $
b100011 (
1"
b100011 !
#292500
0"
#293000
b100100 $
b100100 (
1"
b100100 !
#293500
0"
#294000
b100101 $
b100101 (
1"
b100101 !
#294500
0"
#295000
b100110 $
b100110 (
1"
b100110 !
#295500
0"
#296000
b100111 $
b100111 (
1"
b100111 !
#296500
0"
#297000
b101000 $
b101000 (
1"
b101000 !
#297500
0"
#298000
b101001 $
b101001 (
1"
b101001 !
#298500
0"
#299000
b101010 $
b101010 (
1"
b101010 !
#299500
0"
#300000
b101011 $
b101011 (
1"
b101011 !
#300500
0"
#301000
b101100 $
b101100 (
1"
b101100 !
#301500
0"
#302000
b101101 $
b101101 (
1"
b101101 !
#302500
0"
#303000
b101110 $
b101110 (
1"
b101110 !
#303500
0"
#304000
b101111 $
b101111 (
1"
b101111 !
#304500
0"
#305000
b110000 $
b110000 (
1"
b110000 !
#305500
0"
#306000
b110001 $
b110001 (
1"
b110001 !
#306500
0"
#307000
b110010 $
b110010 (
1"
b110010 !
#307500
0"
#308000
b110011 $
b110011 (
1"
b110011 !
#308500
0"
#309000
b110100 $
b110100 (
1"
b110100 !
#309500
0"
#310000
b110101 $
b110101 (
1"
b110101 !
#310500
0"
#311000
b110110 $
b110110 (
1"
b110110 !
#311500
0"
#312000
b110111 $
b110111 (
1"
b110111 !
#312500
0"
#313000
b111000 $
b111000 (
1"
b111000 !
#313500
0"
#314000
b111001 $
b111001 (
1"
b111001 !
#314500
0"
#315000
b111010 $
b111010 (
1"
b111010 !
#315500
0"
#316000
b111011 $
b111011 (
1"
b111011 !
#316500
0"
#317000
b111100 $
b111100 (
1"
b111100 !
#317500
0"
#318000
b111101 $
b111101 (
1"
b111101 !
#318500
0"
#319000
b111110 $
b111110 (
1"
b111110 !
#319500
0"
#320000
b111111 $
b111111 (
1"
b111111 !
#320500
0"
#321000
b1000000 $
b1000000 (
1"
b1000000 !
#321500
0"
#322000
b1000001 $
b1000001 (
1"
b1000001 !
#322500
0"
#323000
b1000010 $
b1000010 (
1"
b1000010 !
#323500
0"
#324000
b1000011 $
b1000011 (
1"
b1000011 !
#324500
0"
#325000
b1000100 $
b1000100 (
1"
b1000100 !
#325500
0"
#326000
b1000101 $
b1000101 (
1"
b1000101 !
#326500
0"
#327000
b1000110 $
b1000110 (
1"
b1000110 !
#327500
0"
#328000
b1000111 $
b1000111 (
1"
b1000111 !
#328500
0"
#329000
b1001000 $
b1001000 (
1"
b1001000 !
#329500
0"
#330000
b1001001 $
b1001001 (
1"
b1001001 !
#330500
0"
#331000
b1001010 $
b1001010 (
1"
b1001010 !
#331500
0"
#332000
b1001011 $
b1001011 (
1"
b1001011 !
#332500
0"
#333000
b1001100 $
b1001100 (
1"
b1001100 !
#333500
0"
#334000
b1001101 $
b1001101 (
1"
b1001101 !
#334500
0"
#335000
b1001110 $
b1001110 (
1"
b1001110 !
#335500
0"
#336000
b1001111 $
b1001111 (
1"
b1001111 !
#336500
0"
#337000
b1010000 $
b1010000 (
1"
b1010000 !
#337500
0"
#338000
b1010001 $
b1010001 (
1"
b1010001 !
#338500
0"
#339000
b1010010 $
b1010010 (
1"
b1010010 !
#339500
0"
#340000
b1010011 $
b1010011 (
1"
b1010011 !
#340500
0"
#341000
b1010100 $
b1010100 (
1"
b1010100 !
#341500
0"
#342000
b1010101 $
b1010101 (
1"
b1010101 !
#342500
0"
#343000
b1010110 $
b1010110 (
1"
b1010110 !
#343500
0"
#344000
b1010111 $
b1010111 (
1"
b1010111 !
#344500
0"
#345000
b1011000 $
b1011000 (
1"
b1011000 !
#345500
0"
#346000
b1011001 $
b1011001 (
1"
b1011001 !
#346500
0"
#347000
b1011010 $
b1011010 (
1"
b1011010 !
#347500
0"
#348000
b1011011 $
b1011011 (
1"
b1011011 !
#348500
0"
#349000
b1011100 $
b1011100 (
1"
b1011100 !
#349500
0"
#350000
b1011101 $
b1011101 (
1"
b1011101 !
#350500
0"
#351000
b1011110 $
b1011110 (
1"
b1011110 !
#351500
0"
#352000
b1011111 $
b1011111 (
1"
b1011111 !
#352500
0"
#353000
b1100000 $
b1100000 (
1"
b1100000 !
#353500
0"
#354000
b1100001 $
b1100001 (
1"
b1100001 !
#354500
0"
#355000
b1100010 $
b1100010 (
1"
b1100010 !
#355500
0"
#356000
b1100011 $
b1100011 (
1"
b1100011 !
#356500
0"
#357000
b1100100 $
b1100100 (
1"
b1100100 !
#357500
0"
#358000
b1100101 $
b1100101 (
1"
b1100101 !
#358500
0"
#359000
b1100110 $
b1100110 (
1"
b1100110 !
#359500
0"
