Lab2/src/SingleBCD.v
`timescale 1ns / 1ps
//////////////////////////////////////////////////////////////////////////////////
// Create Date: 01/01/2025 02:14:43 AM
// Design Name: BCD_Counter
// Module Name: SingleBCD
// Project Name: BCD_Counter
// Target Devices: Basys3
// Tool Versions: 2023.2
// Description: A single BCD counter module for 1 digit in a 4 digit BCD counter
//////////////////////////////////////////////////////////////////////////////////


module SingleBCD (
    input  wire       Trigger,
    input  wire       Clk,
    input  wire       Reset,
    input  wire       Cin,
    output wire [3:0] DataOut,
    output wire       Cout
);
  // Add your code here
  reg [3:0] dataOut = 4'b0000;
  assign DataOut = dataOut;
  assign Cout = (dataOut + (Trigger & ~Reset) + (Cin & ~Reset)) > 4'b1001;

  always @(posedge Clk) begin
    if (Reset) begin
      dataOut <= 4'b0000;
    end else begin
      dataOut <= (dataOut + (Trigger & ~Reset) + (Cin & ~Reset))%10;
    end
  end
  // End of your code
endmodule

Lab2/src/FourBCD.v
`timescale 1ns / 1ps
//////////////////////////////////////////////////////////////////////////////////
// Create Date: 01/01/2025 02:15:10 AM
// Design Name: BCD_Counter
// Module Name: FourBCD
// Project Name: BCD_Counter
// Target Devices: Basys3
// Tool Versions: 2023.2
// Description: The Four Digit BCD Counter Module
//////////////////////////////////////////////////////////////////////////////////


module FourBCD (
    input wire [3:0] Trigger,
    input wire Clk,
    input wire Reset,
    output wire [15:0] DataOut
);
  // Add your code here
  // Internal signals for carry propagation between digits;
  wire carry1, carry2, carry3, carry4;

  // Instantiate 4 SingleBCD counters for each digit
  SingleBCD digit0 (
      .Trigger(Trigger[0]),       // Trigger for digit 0
      .Clk(Clk),                  // System clock
      .Reset(Reset),              // Reset signal
      .Cin(1'b0),                 // No carry-in for the least significant digit
      .DataOut(DataOut[3:0]),     // BCD output for digit 0
      .Cout(carry1)         // Carry-out from digit 0
  );

  SingleBCD digit1 (
      .Trigger(Trigger[1]), // Trigger for digit 1 or carry-in from digit 0
      .Clk(Clk),                           // System clock
      .Reset(Reset),                       // Reset signal
      .Cin(carry1),                  // Carry-in from digit 0
      .DataOut(DataOut[7:4]),              // BCD output for digit 1
      .Cout(carry2)                  // Carry-out from digit 1
  );

  SingleBCD digit2 (
      .Trigger(Trigger[2]), // Trigger for digit 2 or carry-in from digit 1
      .Clk(Clk),                           // System clock
      .Reset(Reset),                       // Reset signal
      .Cin(carry2),                  // Carry-in from digit 1
      .DataOut(DataOut[11:8]),             // BCD output for digit 2
      .Cout(carry3)                  // Carry-out from digit 2
  );

  SingleBCD digit3 (
      .Trigger(Trigger[3]), // Trigger for digit 3 or carry-in from digit 2
      .Clk(Clk),                           // System clock
      .Reset(Reset),                       // Reset signal
      .Cin(carry3),                  // Carry-in from digit 2
      .DataOut(DataOut[15:12]),            // BCD output for digit 3
      .Cout(carry4)                  // Carry-out from digit 3 (not used here)
  );
  
  // End of your code
endmodule

Lab2/sim/FourBCDTB.v
`timescale 1ns / 1ps
//////////////////////////////////////////////////////////////////////////////////
// Create Date: 01/09/2025 03:30:01 PM
// Design Name: BCD_Counter
// Module Name: FourBCDTB
// Project Name: BCD_Counter
// Target Devices: Basys3
// Tool Versions: 2023.2
// Description: The Testbench for the FourBCD module
//////////////////////////////////////////////////////////////////////////////////


module FourBCDTB ();
  // reg/wire declaration
  reg  [ 3:0] Trigger;
  reg         Clk;
  reg         Reset;
  wire [15:0] DataOut;

  // instantiate the Multiplexer module
  FourBCD FourBCDInst (
      .Trigger(Trigger),
      .Clk(Clk),
      .Reset(Reset),
      .DataOut(DataOut)
  );
  // instantiate variable
  integer flag = 0;
  integer TestCaseNo = 0;
  integer i;
  integer sum = 0;
  integer BCD_SUM = 0;

  // task to check the output
  task check_output;
    input integer TestCaseNo;
    input reg [15:0] expected_DataOut;  // Expected output
    begin
      if (DataOut !== expected_DataOut) begin
        $error("ERROR: TestCaseNo %0d | DataOut = %b (Expected: %b)", TestCaseNo, $time, DataOut,
               expected_DataOut);
        flag = 1;
      end
    end
  endtask

  localparam CLK_PERIOD = 2;
  always #(CLK_PERIOD / 2.0) Clk = ~Clk;

  // test cases
  initial begin
    Clk = 0;
    Reset = 0;
    Trigger = 0;
    #(CLK_PERIOD + 0.1);
    Reset = 1;
    #(CLK_PERIOD);
    Reset   = 0;
    Trigger = 15;
    check_output(0, 0);
    for (i = 0; i < 10; i = i + 1) begin
      #(CLK_PERIOD);
      sum = (sum + 1111) % 10000;
      BCD_SUM = sum%10 + (sum/10)%10*16 + (sum/100)%10*256 + (sum/1000)%10*4096;
      check_output(i + 1, BCD_SUM);
    end
    if (flag == 0) begin
      $display("All test cases pass");
    end else begin
      $display("Some test cases fail");
    end
    $finish;
  end
endmodule

Lab2/cocotb/FourBCDTB/waveform.vcd
$date
	Mon Jan 27 23:20:34 2025
$end
$version
	Icarus Verilog
$end
$timescale
	1ps
$end
$scope module FourBCDTB $end
$var wire 1 ! Clk $end
$var wire 1 " Reset $end
$var wire 4 # Trigger [3:0] $end
$var wire 16 $ DataOut [15:0] $end
$scope module FourBCDInst $end
$var wire 1 ! Clk $end
$var wire 1 " Reset $end
$var wire 4 % Trigger [3:0] $end
$var wire 1 & carry4 $end
$var wire 1 ' carry3 $end
$var wire 1 ( carry2 $end
$var wire 1 ) carry1 $end
$var wire 16 * DataOut [15:0] $end
$scope module digit0 $end
$var wire 1 + Cin $end
$var wire 1 ! Clk $end
$var wire 4 , DataOut [3:0] $end
$var wire 1 " Reset $end
$var wire 1 - Trigger $end
$var wire 1 ) Cout $end
$var reg 4 . dataOut [3:0] $end
$upscope $end
$scope module digit1 $end
$var wire 1 ) Cin $end
$var wire 1 ! Clk $end
$var wire 4 / DataOut [3:0] $end
$var wire 1 " Reset $end
$var wire 1 0 Trigger $end
$var wire 1 ( Cout $end
$var reg 4 1 dataOut [3:0] $end
$upscope $end
$scope module digit2 $end
$var wire 1 ( Cin $end
$var wire 1 ! Clk $end
$var wire 4 2 DataOut [3:0] $end
$var wire 1 " Reset $end
$var wire 1 3 Trigger $end
$var wire 1 ' Cout $end
$var reg 4 4 dataOut [3:0] $end
$upscope $end
$scope module digit3 $end
$var wire 1 ' Cin $end
$var wire 1 ! Clk $end
$var wire 4 5 DataOut [3:0] $end
$var wire 1 " Reset $end
$var wire 1 6 Trigger $end
$var wire 1 & Cout $end
$var reg 4 7 dataOut [3:0] $end
$upscope $end
$upscope $end
$upscope $end
$enddefinitions $end
$comment Show the parameter values. $end
$dumpall
$end
#0
$dumpvars
bx 7
x6
bx 5
bx 4
x3
bx 2
bx 1
00
bx /
b0 .
0-
b0 ,
0+
bx0000 *
0)
x(
x'
x&
b0 %
bx0000 $
b0 #
0"
1!
$end
#500
0!
#1000
1!
#1200
1"
#1500
0!
#2000
03
06
0(
b0 /
b0 1
0'
b0 2
b0 4
0&
b0 $
b0 *
b0 5
b0 7
1!
#2200
10
13
16
1-
b1111 #
b1111 %
0"
#2500
0!
#3000
b1 5
b1 7
b1 2
b1 4
b1 /
b1 1
b1000100010001 $
b1000100010001 *
b1 ,
b1 .
1!
#3500
0!
#4000
b10 ,
b10 .
b10 /
b10 1
b10 2
b10 4
b10001000100010 $
b10001000100010 *
b10 5
b10 7
1!
#4500
0!
#5000
b11 5
b11 7
b11 2
b11 4
b11 /
b11 1
b11001100110011 $
b11001100110011 *
b11 ,
b11 .
1!
#5500
0!
#6000
b100 ,
b100 .
b100 /
b100 1
b100 2
b100 4
b100010001000100 $
b100010001000100 *
b100 5
b100 7
1!
#6500
0!
#7000
b101 5
b101 7
b101 2
b101 4
b101 /
b101 1
b101010101010101 $
b101010101010101 *
b101 ,
b101 .
1!
#7500
0!
#8000
b110 ,
b110 .
b110 /
b110 1
b110 2
b110 4
b110011001100110 $
b110011001100110 *
b110 5
b110 7
1!
#8500
0!
#9000
b111 5
b111 7
b111 2
b111 4
b111 /
b111 1
b111011101110111 $
b111011101110111 *
b111 ,
b111 .
1!
#9500
0!
#10000
b1000 ,
b1000 .
b1000 /
b1000 1
b1000 2
b1000 4
b1000100010001000 $
b1000100010001000 *
b1000 5
b1000 7
1!
#10500
0!
#11000
1&
b1001 5
b1001 7
1'
b1001 2
b1001 4
1(
b1001 /
b1001 1
1)
b1001100110011001 $
b1001100110011001 *
b1001 ,
b1001 .
1!
#11500
0!
#12000
0)
b0 ,
b0 .
0(
b1 /
b1 1
0'
b1 2
b1 4
0&
b1000100010000 $
b1000100010000 *
b1 5
b1 7
1!
