Lab4/Exercise1/src/ROMUnit.v
`timescale 1ns / 1ps
//////////////////////////////////////////////////////////////////////////////////
// Create Date: 01/15/2025 09:47:52 PM
// Design Name: BinaryToDecimal
// Module Name: ROMUnit
// Project Name: BinaryToDecimal
// Target Devices: Basys3
// Tool Versions: 2023.2
// Description: The ROM Unit for the Binary to Decimal conversion Module.
//              This version implements a synchronous ROM that outputs a 16-bit
//              value. In this example, the ROM is preloaded with the ASCII codes
//              for the two-digit decimal representation of numbers 0-63.
//////////////////////////////////////////////////////////////////////////////////

module ROMUnit (
    input  wire [5:0] Address,  // Address selects one of 64 words
    input  wire       Clk,      // Synchronous clock
    input  wire       Reset,    // Active-high reset
    output wire [15:0] DataOut  // 16-bit output (e.g. two ASCII characters)
);
    reg [15:0] mem [63:0];
    
    initial begin
        $readmemb("D:/HW_lab/lab/Lab4/Exercise1/src/rom.mem", mem);
    end
    
    reg [15:0] dataReg;
    assign DataOut = dataReg;

    always @(posedge Clk) begin
        if (Reset)
            dataReg <= 16'b0;
        else
            dataReg <= mem[Address];
    end

`ifdef COCOTB_SIM
  // For simulation purposes, dump waveform data to a VCD file.
  initial begin
    $dumpfile("waveform.vcd");
    $dumpvars(0, ROMUnit);
  end
`endif

endmodule

Lab4/Exercise1/cocotb/ROMUnitTB/waveform.vcd
$date
	Mon Feb 03 18:18:37 2025
$end
$version
	Icarus Verilog
$end
$timescale
	1ps
$end
$scope module ROMUnit $end
$var wire 6 ! Address [5:0] $end
$var wire 1 " Clk $end
$var wire 16 # DataOut [15:0] $end
$var wire 1 $ Reset $end
$var reg 16 % dataReg [15:0] $end
$upscope $end
$enddefinitions $end
$comment Show the parameter values. $end
$dumpall
$end
#0
$dumpvars
b0 %
1$
b0 #
1"
b0 !
$end
#500
0"
#1000
1"
0$
#1500
0"
#2000
b1 #
b1 %
1"
b1 !
#2500
0"
#3000
b10 #
b10 %
1"
b10 !
#3500
0"
#4000
b11 #
b11 %
1"
b11 !
#4500
0"
#5000
b100 #
b100 %
1"
b100 !
#5500
0"
#6000
b101 #
b101 %
1"
b101 !
#6500
0"
#7000
b110 #
b110 %
1"
b110 !
#7500
0"
#8000
b111 #
b111 %
1"
b111 !
#8500
0"
#9000
b1000 #
b1000 %
1"
b1000 !
#9500
0"
#10000
b1001 #
b1001 %
1"
b1001 !
#10500
0"
#11000
b10000 #
b10000 %
1"
b1010 !
#11500
0"
#12000
b10001 #
b10001 %
1"
b1011 !
#12500
0"
#13000
b10010 #
b10010 %
1"
b1100 !
#13500
0"
#14000
b10011 #
b10011 %
1"
b1101 !
#14500
0"
#15000
b10100 #
b10100 %
1"
b1110 !
#15500
0"
#16000
b10101 #
b10101 %
1"
b1111 !
#16500
0"
#17000
b10110 #
b10110 %
1"
b10000 !
#17500
0"
#18000
b10111 #
b10111 %
1"
b10001 !
#18500
0"
#19000
b11000 #
b11000 %
1"
b10010 !
#19500
0"
#20000
b11001 #
b11001 %
1"
b10011 !
#20500
0"
#21000
b100000 #
b100000 %
1"
b10100 !
#21500
0"
#22000
b100001 #
b100001 %
1"
b10101 !
#22500
0"
#23000
b100010 #
b100010 %
1"
b10110 !
#23500
0"
#24000
b100011 #
b100011 %
1"
b10111 !
#24500
0"
#25000
b100100 #
b100100 %
1"
b11000 !
#25500
0"
#26000
b100101 #
b100101 %
1"
b11001 !
#26500
0"
#27000
b100110 #
b100110 %
1"
b11010 !
#27500
0"
#28000
b100111 #
b100111 %
1"
b11011 !
#28500
0"
#29000
b101000 #
b101000 %
1"
b11100 !
#29500
0"
#30000
b101001 #
b101001 %
1"
b11101 !
#30500
0"
#31000
b110000 #
b110000 %
1"
b11110 !
#31500
0"
#32000
b110001 #
b110001 %
1"
b11111 !
#32500
0"
#33000
b110010 #
b110010 %
1"
b100000 !
#33500
0"
#34000
b110011 #
b110011 %
1"
b100001 !
#34500
0"
#35000
b110100 #
b110100 %
1"
b100010 !
#35500
0"
#36000
b110101 #
b110101 %
1"
b100011 !
#36500
0"
#37000
b110110 #
b110110 %
1"
b100100 !
#37500
0"
#38000
b110111 #
b110111 %
1"
b100101 !
#38500
0"
#39000
b111000 #
b111000 %
1"
b100110 !
#39500
0"
#40000
b111001 #
b111001 %
1"
b100111 !
#40500
0"
#41000
b1000000 #
b1000000 %
1"
b101000 !
#41500
0"
#42000
b1000001 #
b1000001 %
1"
b101001 !
#42500
0"
#43000
b1000010 #
b1000010 %
1"
b101010 !
#43500
0"
#44000
b1000011 #
b1000011 %
1"
b101011 !
#44500
0"
#45000
b1000100 #
b1000100 %
1"
b101100 !
#45500
0"
#46000
b1000101 #
b1000101 %
1"
b101101 !
#46500
0"
#47000
b1000110 #
b1000110 %
1"
b101110 !
#47500
0"
#48000
b1000111 #
b1000111 %
1"
b101111 !
#48500
0"
#49000
b1001000 #
b1001000 %
1"
b110000 !
#49500
0"
#50000
b1001001 #
b1001001 %
1"
b110001 !
#50500
0"
#51000
b1010000 #
b1010000 %
1"
b110010 !
#51500
0"
#52000
b1010001 #
b1010001 %
1"
b110011 !
#52500
0"
#53000
b1010010 #
b1010010 %
1"
b110100 !
#53500
0"
#54000
b1010011 #
b1010011 %
1"
b110101 !
#54500
0"
#55000
b1010100 #
b1010100 %
1"
b110110 !
#55500
0"
#56000
b1010101 #
b1010101 %
1"
b110111 !
#56500
0"
#57000
b1010110 #
b1010110 %
1"
b111000 !
#57500
0"
#58000
b1010111 #
b1010111 %
1"
b111001 !
#58500
0"
#59000
b1011000 #
b1011000 %
1"
b111010 !
#59500
0"
#60000
b1011001 #
b1011001 %
1"
b111011 !
#60500
0"
#61000
b1100000 #
b1100000 %
1"
b111100 !
#61500
0"
#62000
b1100001 #
b1100001 %
1"
b111101 !
#62500
0"
#63000
b1100010 #
b1100010 %
1"
b111110 !
#63500
0"
#64000
b1100011 #
b1100011 %
1"
b111111 !
